tortoise_data_migration/__init__.py
tortoise_data_migration/exception.py
tortoise_data_migration/models.py
tortoise_data_migration-1.0.1.dist-info/METADATA
tortoise_data_migration-1.0.1.dist-info/WHEEL
tortoise_data_migration-1.0.1.dist-info/LICENSE
tortoise_data_migration-1.0.1.dist-info/RECORD
