Metadata-Version: 2.1
Name: tortoise-data-migration
Version: 1.0.1
Summary: Tortoise migrations for data, not structure
Home-page: https://github.com/Ekumen-OS/tortoise-data-migration
License: MIT
Keywords: migrations,tortoise,data-migrations
Author: Guillermo Manzato
Author-email: manzato@ekumenlabs.com
Requires-Python: >=3.8,<4.0
Classifier: Development Status :: 4 - Beta
Classifier: Framework :: AsyncIO
Classifier: Intended Audience :: Developers
Classifier: License :: OSI Approved :: MIT License
Classifier: Programming Language :: Python :: 3
Classifier: Programming Language :: Python :: 3.8
Classifier: Programming Language :: Python :: 3.9
Classifier: Programming Language :: Python :: 3.10
Classifier: Programming Language :: Python :: 3.11
Classifier: Topic :: Database
Requires-Dist: tortoise-orm (>=0.17.5,<0.20)
Project-URL: Documentation, https://github.com/Ekumen-OS/tortoise-data-migration
Project-URL: Repository, https://github.com/Ekumen-OS/tortoise-data-migration
